extension_audit/__init__.py
extension_audit/analysis.py
extension_audit/app.py
extension_audit/flow_processor.py
extension_audit/grapher.py
extension_audit/main.py
extension_audit-1.1.0.dist-info/LICENSE
extension_audit-1.1.0.dist-info/METADATA
extension_audit-1.1.0.dist-info/WHEEL
extension_audit-1.1.0.dist-info/entry_points.txt
extension_audit-1.1.0.dist-info/top_level.txt
extension_audit-1.1.0.dist-info/RECORD
